README.md
setup.py
zkmo/__init__.py
zkmo/mo.py
zkmo.egg-info/PKG-INFO
zkmo.egg-info/SOURCES.txt
zkmo.egg-info/dependency_links.txt
zkmo.egg-info/not-zip-safe
zkmo.egg-info/requires.txt
zkmo.egg-info/top_level.txt
zkmo/aio/__init__.py
zkmo/aio/aio.py
zkmo_bak/__init__.py
zkmo_bak/mo.py
zkmo_bak/aio/__init__.py
zkmo_bak/aio/aio.py